Workbook
Name aporte: Planilha1!$E$5:$E$5
Name patrimonio: Planilha1!$E$8:$E$8
Name qtd_anos: Planilha1!$E$6:$E$6
Name rendimento_carteira: Planilha1!$J$6:$J$6
Name salario: Planilha1!$J$5:$J$5
Name sugestao_investimento: Planilha1!$J$7:$J$7
Name taxa_mensal: Planilha1!$E$7:$E$7

Sheet Planilha1
B4: Investimento Mensal | H4: Configurações
B5: Quanto investir por mês? | E5: 500 | H5: Salário | J5: 5000
B6: Por quantos anos? | E6: 5 | H6: Rendimento Carteira | J6: 0.0089
B7: Taxa de rendimento mensal? | E7: 0.01079 | H7: Sugestão de Investimento | J7: =J5*30% -> 1500
B8: Patrimônio acumulado? | E8: {=FV(taxa_mensal,qtd_anos*12,aporte*-1)} -> 41888.457
B9: Dividendos mensais? | E9: {=patrimonio*rendimento_carteira} -> 372.80727
B11: Cenários | F11: Dividendo
A12: 2 | B12: Quanto em 2 anos? | E12: =FV($E$7,$A12*12,$E$5*-1) -> 13613.814 | F12: {=E12*rendimento_carteira} -> 121.16294
A13: 5 | B13: Quanto em 5 anos? | E13: =FV($E$7,$A13*12,$E$5*-1) -> 41888.457 | F13: {=E13*rendimento_carteira} -> 372.80727
A14: 10 | B14: Quanto em 10 anos? | E14: =FV($E$7,$A14*12,$E$5*-1) -> 121642.11 | F14: {=E14*rendimento_carteira} -> 1082.6147
A15: 20 | B15: Quanto em 20 anos? | E15: =FV($E$7,$A15*12,$E$5*-1) -> 562599.2 | F15: {=E15*rendimento_carteira} -> 5007.1329
A16: 30 | B16: Quanto em 30 anos? | E16: =FV($E$7,$A16*12,$E$5*-1) -> 2161084.8 | F16: {=E16*rendimento_carteira} -> 19233.655
B22: PERFIL: | H22: MODERADO
B23: VALOR A SER INVESTIDO POR MÊS: | H23: {=aporte} -> 500
B25: TIPOS DE FII | F25: Percentual sugerido | H25: Valores
B26: PAPEL | F26: =VLOOKUP($H$22&"-"&B26,Planilha2!$A:$D,4,FALSE) -> 0.32 | H26: =F26*$H$23 -> 160
B27: TIJOLO | F27: =VLOOKUP($H$22&"-"&B27,Planilha2!$A:$D,4,FALSE) -> 0.35 | H27: =F27*$H$23 -> 175
B28: HÍBRIDOS | F28: =VLOOKUP($H$22&"-"&B28,Planilha2!$A:$D,4,FALSE) -> 0.08 | H28: =F28*$H$23 -> 40
B29: FOFs | F29: =VLOOKUP($H$22&"-"&B29,Planilha2!$A:$D,4,FALSE) -> 0.05 | H29: =F29*$H$23 -> 25
B30: DESENVOLVIMENTO | F30: =VLOOKUP($H$22&"-"&B30,Planilha2!$A:$D,4,FALSE) -> 0.1 | H30: =F30*$H$23 -> 50
B31: HOTELARIAS | F31: =VLOOKUP($H$22&"-"&B31,Planilha2!$A:$D,4,FALSE) -> 0.1 | H31: =F31*$H$23 -> 50
B32: SOMA: | H32: =SUM(H26:H31) -> 500

Sheet Planilha2
A3: Chave | B3: Perfil | C3: Tipos de FII | D3: % | H3: %
A4: =B4&"-"&C4 -> CONSERVADOR-PAPEL | B4: CONSERVADOR | C4: PAPEL | D4: 0.3 | G4: CONSERVADOR-PAPEL | H4: =VLOOKUP(G4,$A:$D,4,FALSE) -> 0.3
A5: =B5&"-"&C5 -> CONSERVADOR-TIJOLO | B5: CONSERVADOR | C5: TIJOLO | D5: 0.5
A6: =B6&"-"&C6 -> CONSERVADOR-HÍBRIDOS | B6: CONSERVADOR | C6: HÍBRIDOS | D6: 0.1
A7: =B7&"-"&C7 -> CONSERVADOR-FOFs | B7: CONSERVADOR | C7: FOFs | D7: 0.1
A8: =B8&"-"&C8 -> CONSERVADOR-DESENVOLVIMENTO | B8: CONSERVADOR | C8: DESENVOLVIMENTO | D8: 0
A9: =B9&"-"&C9 -> CONSERVADOR-HOTELARIAS | B9: CONSERVADOR | C9: HOTELARIAS | D9: 0
A10: =B10&"-"&C10 -> MODERADO-PAPEL | B10: MODERADO | C10: PAPEL | D10: 0.32
A11: =B11&"-"&C11 -> MODERADO-TIJOLO | B11: MODERADO | C11: TIJOLO | D11: 0.35
A12: =B12&"-"&C12 -> MODERADO-HÍBRIDOS | B12: MODERADO | C12: HÍBRIDOS | D12: 0.08
A13: =B13&"-"&C13 -> MODERADO-FOFs | B13: MODERADO | C13: FOFs | D13: 0.05
A14: =B14&"-"&C14 -> MODERADO-DESENVOLVIMENTO | B14: MODERADO | C14: DESENVOLVIMENTO | D14: 0.1
A15: =B15&"-"&C15 -> MODERADO-HOTELARIAS | B15: MODERADO | C15: HOTELARIAS | D15: 0.1
A16: =B16&"-"&C16 -> AGRESSIVO-PAPEL | B16: AGRESSIVO | C16: PAPEL | D16: 0.5
... A21: =B21&"-"&C21 -> AGRESSIVO-HOTELARIAS | B21: AGRESSIVO | C21: HOTELARIAS | D21: 0.1
